ws_dash_components/AgGrid.py
ws_dash_components/RenderJson.py
ws_dash_components/S3Upload.py
ws_dash_components/S3Uploader.py
ws_dash_components/S3Uploaderr.py
ws_dash_components/__init__.py
ws_dash_components/_imports_.py
ws_dash_components/metadata.json
ws_dash_components/package-info.json
ws_dash_components/ws_dash_components.min.js
ws_dash_components/ws_dash_components.min.js.LICENSE.txt
ws_dash_components/ws_dash_components.min.js.map
ws_dash_components-0.1.0.dist-info/LICENSE
ws_dash_components-0.1.0.dist-info/WHEEL
ws_dash_components-0.1.0.dist-info/METADATA
ws_dash_components-0.1.0.dist-info/RECORD
